cython_munkres.cp35-win_amd64.pyd
csm/__init__.py
csm/__main__.py
csm/fast.cp35-win_amd64.pyd
csm/version.py
csm/CPP_wrapper/fast.cpp
csm/calculations/__init__.py
csm/calculations/basic_calculations.py
csm/calculations/constants.py
csm/calculations/data_classes.py
csm/calculations/exact_calculations.py
csm/calculations/trivial_calculations.py
csm/calculations/approx/__init__.py
csm/calculations/approx/approximators.py
csm/calculations/approx/dirs.py
csm/input_output/__init__.py
csm/input_output/arguments.py
csm/input_output/formatters.py
csm/input_output/readers.py
csm/input_output/writers.py
csm/main/__init__.py
csm/main/csm_run.py
csm/molecule/__init__.py
csm/molecule/atom.py
csm/molecule/molecule.py
csm/molecule/normalizations.py
proteincsm-1.0.1.dist-info/LICENSE.md
proteincsm-1.0.1.dist-info/METADATA
proteincsm-1.0.1.dist-info/WHEEL
proteincsm-1.0.1.dist-info/entry_points.txt
proteincsm-1.0.1.dist-info/top_level.txt
proteincsm-1.0.1.dist-info/RECORD
