Metadata-Version: 2.1
Name: proteincsm
Version: 1.0.1
Summary: The Continuous Symmetry Measure for Proteins
Home-page: https://github.com/continuous-symmetry/proteincsm/tree/v1.0.1
Author: The Research Software Company
Author-email: itay@chelem.co.il
License: GPL2
Platform: UNKNOWN
Classifier: Development Status :: 4 - Beta
Classifier: Environment :: Console
Classifier: Intended Audience :: Science/Research
Classifier: License :: OSI Approved :: GNU General Public License v2 (GPLv2)
Classifier: Operating System :: OS Independent
Classifier: Programming Language :: Python
Classifier: Programming Language :: Python :: 3.5
Classifier: Topic :: Scientific/Engineering :: Chemistry
Requires-Dist: numpy (>=1.10)
Requires-Dist: openbabel (>=2.4.0)
